[{"name":"/App/Plan Selection","nodes":[{"id":"da2f184e-7e3b-9508-db56-b84e66ff36d5","type":"Page","parameters":{},"ports":[],"children":[{"id":"def16a0a-5082-1fcd-25a9-f79ed6807e12","type":"/Header","parameters":{},"ports":[],"children":[]},{"id":"bd28ca07-ab71-743a-e4ab-e97f623732db","type":"Group","parameters":{"paddingLeft":{"value":5,"unit":"px"},"paddingRight":{"value":5,"unit":"px"}},"ports":[],"children":[{"id":"8465f008-9f5a-1568-b473-b8efc5986fe5","type":"Group","parameters":{"sizeMode":"contentHeight","width":{"value":100,"unit":"%"},"boxShadowEnabled":true,"borderRadius":{"value":10,"unit":"px"},"paddingLeft":{"value":10,"unit":"px"},"paddingTop":{"value":10,"unit":"px"},"paddingBottom":{"value":10,"unit":"px"},"paddingRight":{"value":10,"unit":"px"},"marginTop":{"value":10,"unit":"px"},"marginBottom":{"value":10,"unit":"px"},"marginLeft":{"value":5,"unit":"px"},"marginRight":{"value":5,"unit":"px"}},"ports":[],"children":[{"id":"b905c488-44d3-e45b-b39d-6043ff0e6a36","type":"Text","parameters":{"text":"Starter Plan","textStyle":"Title Medium"},"ports":[],"children":[]},{"id":"102a4552-1a22-49ed-1a1e-8d91867227aa","type":"Text","parameters":{"text":"+ Access To AIRDA.AI\n+ Basic Support\n+ Usage Of All AI Studios*","marginTop":{"value":2,"unit":"px"},"marginBottom":{"value":2,"unit":"px"}},"ports":[],"children":[]},{"id":"4c4dd82e-299f-64a9-302d-83f0f7835318","type":"Text","parameters":{"fontSize":{"value":9,"unit":"px"},"text":"*Fair Usage Policy Of 1000 Images Per Month","marginTop":{"value":2,"unit":"px"}},"ports":[],"children":[]},{"id":"34302083-bcc3-b68c-66a2-635d2b7af816","type":"Group","parameters":{"flexDirection":"row","marginTop":{"value":5,"unit":"px"},"marginBottom":{"value":5,"unit":"px"},"marginLeft":{"value":5,"unit":"px"}},"ports":[],"children":[{"id":"9123d752-0eef-d87f-db78-58fa2760d52e","type":"Text","parameters":{"text":"19.99","textStyle":"Title Medium","color":"Black","sizeMode":"contentSize"},"ports":[],"children":[]},{"id":"1cd929ab-3553-5c70-b798-dce9676e6d71","type":"Text","parameters":{"text":"PER MONTH","textStyle":"Title Medium","color":"Black","sizeMode":"contentSize","marginLeft":{"value":5,"unit":"px"},"fontSize":{"value":8,"unit":"px"},"alignY":"center"},"ports":[],"children":[]}]},{"id":"eaff107b-425d-9958-f9f5-ef81ba74d3e3","type":"net.noodl.controls.button","parameters":{"backgroundColor":"transparent","label":"Get Started","color":"Black","borderStyle":"solid","marginTop":{"value":5,"unit":"px"},"marginBottom":{"value":10,"unit":"px"}},"ports":[],"children":[]}]},{"id":"bf36dacd-111c-b5a8-08fd-26efc4f631c9","type":"Group","parameters":{"sizeMode":"contentHeight","width":{"value":100,"unit":"%"},"boxShadowEnabled":true,"borderRadius":{"value":10,"unit":"px"},"paddingLeft":{"value":10,"unit":"px"},"paddingTop":{"value":10,"unit":"px"},"paddingBottom":{"value":10,"unit":"px"},"paddingRight":{"value":10,"unit":"px"},"marginTop":{"value":10,"unit":"px"},"marginBottom":{"value":10,"unit":"px"},"marginLeft":{"value":5,"unit":"px"},"marginRight":{"value":5,"unit":"px"},"backgroundColor":"Primary"},"ports":[],"children":[{"id":"f2152a00-892c-c62b-1fbb-7e5ced9899a3","type":"Group","parameters":{"flexDirection":"row"},"ports":[],"children":[{"id":"e3ccd0b9-1637-ad95-035c-ed93ab79d95c","type":"Text","parameters":{"text":"PRO+ Plan","textStyle":"Title Medium","color":"White","sizeMode":"contentSize"},"ports":[],"children":[]},{"id":"05fe115b-b6a5-3c65-9ea0-29cac3811de7","type":"Text","parameters":{"text":"MOST POPULAR PACKAGE","textStyle":"Title Medium","color":"White","sizeMode":"contentSize","marginLeft":{"value":15,"unit":"px"},"fontSize":{"value":8,"unit":"px"},"alignY":"center"},"ports":[],"children":[]}]},{"id":"56086305-540c-9404-4003-02feab36e4f4","type":"Text","parameters":{"text":"+ Everything In The Starter Plan\n+ 3 Bespoke Designs Packages Monthly\n+ Priority Access\n+ Priority Support","color":"White"},"ports":[],"children":[]},{"id":"b9c22431-b361-dfd7-c0a8-86f4b2aba105","type":"Group","parameters":{"flexDirection":"row","marginTop":{"value":5,"unit":"px"},"marginBottom":{"value":5,"unit":"px"},"marginLeft":{"value":5,"unit":"px"}},"ports":[],"children":[{"id":"671970b5-bac3-7f94-d17e-6d82010144a5","type":"Text","parameters":{"text":"74.99","textStyle":"Title Medium","color":"White","sizeMode":"contentSize"},"ports":[],"children":[]},{"id":"e76a022f-9f9f-6ecf-5e3d-19aee655c863","type":"Text","parameters":{"text":"PER MONTH","textStyle":"Title Medium","color":"White","sizeMode":"contentSize","marginLeft":{"value":5,"unit":"px"},"fontSize":{"value":8,"unit":"px"},"alignY":"center"},"ports":[],"children":[]}]},{"id":"a3a424f4-81a3-1c25-f130-08cc32dbaeb2","type":"net.noodl.controls.button","parameters":{"backgroundColor":"White","label":"Get Started","color":"Black","marginTop":{"value":5,"unit":"px"},"marginBottom":{"value":10,"unit":"px"}},"ports":[],"children":[]}]},{"id":"3b4cf8be-6a05-ca7d-7ea9-4db3879b7fb1","type":"Group","parameters":{"sizeMode":"contentHeight","width":{"value":100,"unit":"%"},"boxShadowEnabled":true,"borderRadius":{"value":10,"unit":"px"},"paddingLeft":{"value":5,"unit":"px"},"paddingTop":{"value":5,"unit":"px"},"paddingBottom":{"value":5,"unit":"px"},"paddingRight":{"value":5,"unit":"px"},"marginTop":{"value":10,"unit":"px"},"marginBottom":{"value":10,"unit":"px"},"marginLeft":{"value":5,"unit":"px"},"marginRight":{"value":5,"unit":"px"}},"ports":[],"children":[{"id":"2a6f07b5-dc6d-f134-9e5c-2baee9b2678b","type":"Group","parameters":{"flexDirection":"row"},"ports":[],"children":[{"id":"8459cdd8-e265-8207-9056-02aded5dd550","type":"Text","parameters":{"text":"Custom Plan","textStyle":"Title Medium","color":"Black","sizeMode":"contentSize"},"ports":[],"children":[]}]},{"id":"9a466479-d67b-e8ec-d7e1-a60cde98a06d","type":"Text","parameters":{"text":"Introducing Our Custom Solutions package, meticulously crafted to suit your unique needs. For a custom monthly fee, unlock a comprehensive suite of services tailored exclusively for you:\n\n+ Custom AI Solutions: Tailored AI solutions designed to perfectly match your business requirements.\n\n+ White Labelling: Seamlessly integrate our cutting-edge AI technologies under your own brand, ensuring a seamless user experience.\n\n+ System Training: Empower your team with dedicated training sessions, ensuring they harness our AI tools to their fullest potential.\n\n+ Priority Support: Gain access to expedited support services, ensuring swift resolution of any inquiries or issues you encounter.\n\nExperience the pinnacle of customization and support with Our Custom Solutions package – your pathway to unparalleled efficiency and success.","color":"Black"},"ports":[],"children":[]},{"id":"6e01c1de-2800-37d3-2b14-a241142847c4","type":"Group","parameters":{"flexDirection":"row","marginTop":{"value":5,"unit":"px"},"marginBottom":{"value":5,"unit":"px"},"marginLeft":{"value":5,"unit":"px"}},"ports":[],"children":[{"id":"6f2c373e-0c50-5f24-60a4-6d0ec86e145d","type":"Text","parameters":{"text":"custom","textStyle":"Title Medium","color":"Black","sizeMode":"contentSize"},"ports":[],"children":[]},{"id":"dd9dc4bd-be2d-bcb7-8a7d-aa07db29dde4","type":"Text","parameters":{"text":"PER MONTH","textStyle":"Title Medium","color":"Black","sizeMode":"contentSize","marginLeft":{"value":5,"unit":"px"},"fontSize":{"value":8,"unit":"px"},"alignY":"center"},"ports":[],"children":[]}]},{"id":"ab461fec-98b9-73b9-144d-77887f91a245","type":"net.noodl.controls.button","parameters":{"backgroundColor":"White","label":"Get Started","color":"Black","marginTop":{"value":5,"unit":"px"},"marginBottom":{"value":10,"unit":"px"},"borderStyle":"solid"},"ports":[],"children":[]}]}]},{"id":"d0e3e81a-f1ad-51ef-2dc1-23a8cbb73157","type":"/Bottom Nav","parameters":{},"ports":[],"children":[]}]},{"id":"37a9b12c-d6b8-b527-6254-560de4176246","type":"PageInputs","parameters":{},"ports":[],"children":[]},{"id":"d4759245-6f03-6eb4-611f-5c773bc443a6","type":"net.noodl.externallink","parameters":{"link":"https://buy.stripe.com/28o4gr2fEggZely4gi","openInNewTab":false},"ports":[],"children":[]},{"id":"95374cb8-7709-59cf-bf09-8b5e4e912594","type":"net.noodl.externallink","parameters":{"link":"https://buy.stripe.com/eVa7sDf2q0i191e145","openInNewTab":false},"ports":[],"children":[]}],"connections":[{"sourceId":"da2f184e-7e3b-9508-db56-b84e66ff36d5","sourcePort":"didMount","targetId":"def16a0a-5082-1fcd-25a9-f79ed6807e12","targetPort":"PAGE LOAD"},{"sourceId":"1cd929ab-3553-5c70-b798-dce9676e6d71","sourcePort":"onClick","targetId":"d4759245-6f03-6eb4-611f-5c773bc443a6","targetPort":"do"},{"sourceId":"a3a424f4-81a3-1c25-f130-08cc32dbaeb2","sourcePort":"onClick","targetId":"95374cb8-7709-59cf-bf09-8b5e4e912594","targetPort":"do"}],"ports":[],"roots":["da2f184e-7e3b-9508-db56-b84e66ff36d5"]}]